MANIFEST.in
setup.py
src/django_counter/__init__.py
src/django_counter/admin.py
src/django_counter/models.py
src/django_counter/tests.py
src/django_counter/testsettings.py
src/django_counter/urls.py
src/django_counter/version.py
src/django_counter/views.py
src/django_counter.egg-info/PKG-INFO
src/django_counter.egg-info/SOURCES.txt
src/django_counter.egg-info/dependency_links.txt
src/django_counter.egg-info/not-zip-safe
src/django_counter.egg-info/requires.txt
src/django_counter.egg-info/top_level.txt
src/django_counter/templates/counter/counter.html
src/django_counter/templatetags/__init__.py
src/django_counter/templatetags/counter_tags.py